olspow/__init__.py
olspow/olspow.py
olspow-1.1.2.dist-info/LICENSE
olspow-1.1.2.dist-info/METADATA
olspow-1.1.2.dist-info/WHEEL
olspow-1.1.2.dist-info/top_level.txt
olspow-1.1.2.dist-info/RECORD
