Metadata-Version: 2.1
Name: olspow
Version: 1.1.2
Summary: Python package for conducting power analysis given ratio metrics, clustered data, and covariate adjustment.
Author-email: "Benjamin S. Knight" <knight.benjamin@gmail.com>
Project-URL: Homepage, https://github.com/b-knight/olspow
Project-URL: Issues, https://github.com/b-knight/olspow/issues
Classifier: Programming Language :: Python :: 3
Classifier: License :: OSI Approved :: MIT License
Classifier: Operating System :: OS Independent
Requires-Python: >=3.9
License-File: LICENSE
Requires-Dist: humanize
Requires-Dist: numpy
Requires-Dist: pandas
Requires-Dist: scipy
Requires-Dist: statsmodels
